{
  "recipes": [
    {
      "id": 1,
      "name": "Apple Frangipan Tart",
      "image": "https://www.themealdb.com/images/media/meals/wxywrq1468235067.jpg"
    },
    {
      "id": 2,
      "name": "Apple & Blackberry Crumble",
      "image": "https://www.themealdb.com/images/media/meals/xvsurr1511719182.jpg"
    },
    {
      "id": 3,
      "name": "Apam balik",
      "image": "https://www.themealdb.com/images/media/meals/adxcbq1619787919.jpg"
    },
    {
      "id": 4,
      "name": "Ayam Percik",
      "image": "https://www.themealdb.com/images/media/meals/020z181619788503.jpg"
    },
    {
      "id": 5,
      "name": "Bakewell tart",
      "image": "https://www.themealdb.com/images/media/meals/wyrqqq1468233628.jpg"
    },
    {
      "id": 6,
      "name": "Bread and Butter Pudding",
      "image": "https://www.themealdb.com/images/media/meals/xqwwpy1483908697.jpg"
    },
    {
      "id": 7,
      "name": "Beef Wellington",
      "image": "https://www.themealdb.com/images/media/meals/vvpprx1487325699.jpg"
    },
    {
      "id": 8,
      "name": "Baingan Bharta",
      "image": "https://www.themealdb.com/images/media/meals/urtpqw1487341253.jpg"
    },
    {
      "id": 9,
      "name": "Beef Brisket Pot Roast",
      "image": "https://www.themealdb.com/images/media/meals/ursuup1487348423.jpg"
    },
    {
      "id": 10,
      "name": "Chocolate Gateau",
      "image": "https://www.themealdb.com/images/media/meals/tqtywx1468317395.jpg"
    },
    {
      "name": "asd",
      "image": "asd",
      "id": 11
    },
    {
      "name": "asd",
      "image": "asd",
      "id": 12
    }
  ]
}